llm_yt_transcript.py
llm_yt_transcript-0.1.0.dist-info/licenses/LICENSE
llm_yt_transcript-0.1.0.dist-info/METADATA
llm_yt_transcript-0.1.0.dist-info/WHEEL
llm_yt_transcript-0.1.0.dist-info/entry_points.txt
llm_yt_transcript-0.1.0.dist-info/top_level.txt
llm_yt_transcript-0.1.0.dist-info/RECORD
