Metadata-Version: 2.4
Name: llm-yt-transcript
Version: 0.1.0
Summary: A LLM plugin for YouTube transcripts as fragments
Author: kj-9
License-Expression: MIT
Project-URL: Homepage, https://github.com/kj-9/llm-yt-transcript
Project-URL: Changelog, https://github.com/kj-9/llm-yt-transcript/releases
Project-URL: Issues, https://github.com/kj-9/llm-yt-transcript/issues
Project-URL: CI, https://github.com/kj-9/llm-yt-transcript/actions
Requires-Python: >=3.10
License-File: LICENSE
Requires-Dist: build>=1.2.2.post1
Requires-Dist: llm>=0.24.2
Requires-Dist: setuptools>=78.1.0
Requires-Dist: wheel>=0.45.1
Requires-Dist: yt-dlp
Dynamic: license-file
